peewee_migrate/__init__.py
peewee_migrate/__main__.py
peewee_migrate/auto.py
peewee_migrate/cli.py
peewee_migrate/compat.py
peewee_migrate/migrator.py
peewee_migrate/router.py
peewee_migrate/template.txt
peewee_migrate2-1.6.5.dist-info/licenses/AUTHORS.rst
peewee_migrate2-1.6.5.dist-info/licenses/LICENSE
peewee_migrate2-1.6.5.dist-info/METADATA
peewee_migrate2-1.6.5.dist-info/WHEEL
peewee_migrate2-1.6.5.dist-info/entry_points.txt
peewee_migrate2-1.6.5.dist-info/top_level.txt
peewee_migrate2-1.6.5.dist-info/RECORD
